phasor_noise/__init__.py
phasor_noise/GUI/__init__.py
phasor_noise/GUI/menu.py
phasor_noise/GUI/platform_specific.py
phasor_noise/analysis/__init__.py
phasor_noise/generator/__init__.py
Phasor_Noise-1.3.1.dist-info/AUTHORS
Phasor_Noise-1.3.1.dist-info/LICENSE
Phasor_Noise-1.3.1.dist-info/METADATA
Phasor_Noise-1.3.1.dist-info/WHEEL
Phasor_Noise-1.3.1.dist-info/pbr.json
Phasor_Noise-1.3.1.dist-info/top_level.txt
Phasor_Noise-1.3.1.dist-info/RECORD
