Metadata-Version: 2.1
Name: Phasor-Noise
Version: 1.3.1
Home-page: https://github.com/etachouzin/phasor_noise
Author: Alexis Le Meur, Etienne Tachouzin, Paul Martin, Guillaume Hisleur, Paul Bedrossian
Author-email: phasor_noise_dev@outlook.fr
Maintainer: Alexis Le Meur, Etienne Tachouzin, Paul Martin, Guillaume Hisleur, Paul Bedrossian
Maintainer-email: phasor_noise_dev@outlook.fr
License: GNU
Keywords: phasor_noise,generator
License-File: LICENSE
License-File: AUTHORS
Requires-Dist: numpy (>=1.24.3)
Requires-Dist: matplotlib (>=3.7.1)
Requires-Dist: pillow (>=9.4.0)
Requires-Dist: scikit-image (>=0.20.0)
Requires-Dist: setuptools (>=66.0.0)
